datamizer/__init__.py
datamizer/datamizer.py
datamizer/helpers.py
datamizer-0.0.3.dist-info/LICENSE
datamizer-0.0.3.dist-info/METADATA
datamizer-0.0.3.dist-info/WHEEL
datamizer-0.0.3.dist-info/top_level.txt
datamizer-0.0.3.dist-info/RECORD
