Metadata-Version: 2.1
Name: datamizer
Version: 0.0.3
Summary: Simple package that lets you change the sensitive data from a .CSV file creating a new file with fake data.  
Author-email: Nicolas Repetto <nicolasre011@gmail.com>
License: MIT License
Project-URL: Homepage, https://github.com/whosgriffith/datamizer
Classifier: Development Status :: 1 - Planning
Classifier: License :: OSI Approved :: MIT License
Classifier: Programming Language :: Python
Classifier: Programming Language :: Python :: 3
Requires-Python: >=3.8
License-File: LICENSE
Requires-Dist: pandas (>=1.5.3)
Requires-Dist: Faker (>=16.6.0)
Provides-Extra: dev
Requires-Dist: pytest ; extra == 'dev'
